db2azure/__init__.py
db2azure/connectors/__init__.py
db2azure/connectors/mssql_connector.py
db2azure/connectors/mysql_connector.py
db2azure/connectors/postgres_connector.py
db2azure/helpers/__init__.py
db2azure/helpers/response/__init__.py
db2azure/helpers/response/response_handler.py
db2azure/helpers/storage/__init__.py
db2azure/helpers/storage/azure_blob_helper.py
db2azure/loaders/__init__.py
db2azure/loaders/mssql_loader.py
db2azure/loaders/mysql_loader.py
db2azure/loaders/postgre_loader.py
db2azure/utils/__init__.py
db2azure/utils/file_utils.py
db2azure/utils/loader_utils.py
DB2Azure-1.1.1.dist-info/LICENSE
DB2Azure-1.1.1.dist-info/METADATA
DB2Azure-1.1.1.dist-info/WHEEL
DB2Azure-1.1.1.dist-info/top_level.txt
DB2Azure-1.1.1.dist-info/RECORD
